kombu_multibroker
