Metadata-Version: 1.0
Name: kombu-multibroker
Version: 0.0.4
Summary: Support for multiple brokers in Kombu
Home-page: http://github.com/rbranson/kombu-multibroker
Author: Rick Branson
Author-email: rick@diodeware.com
License: BSD
Keywords: kombu broker amqp
Platform: UNKNOWN
Classifier: Development Status :: 3 - Alpha
Classifier: License :: OSI Approved :: BSD License
Classifier: Operating System :: OS Independent
Classifier: Programming Language :: Python
Classifier: Programming Language :: Python :: 3
Classifier: Programming Language :: Python :: 2.7
Classifier: Programming Language :: Python :: 2.6
Classifier: Programming Language :: Python :: 2.5
Classifier: Programming Language :: Python :: 2
Classifier: Programming Language :: Python :: Implementation :: CPython
Classifier: Programming Language :: Python :: Implementation :: PyPy
Classifier: Programming Language :: Python :: Implementation :: Jython
Classifier: Intended Audience :: Developers
Classifier: Topic :: Communications
Classifier: Topic :: System :: Distributed Computing
Classifier: Topic :: System :: Networking
Classifier: Topic :: Software Development :: Libraries :: Python Modules
